<annotation>
	<folder>train</folder>
	<filename>left001822.png</filename>
	<path>/home/neo/Desktop/datat/train/left001822.png</path>
	<source>
		<database>Unknown</database>
	</source>
	<size>
		<width>2208</width>
		<height>1242</height>
		<depth>3</depth>
	</size>
	<segmented>0</segmented>
	<object>
		<name>object</name>
		<pose>Unspecified</pose>
		<truncated>0</truncated>
		<difficult>0</difficult>
		<bndbox>
			<xmin>1735</xmin>
			<ymin>214</ymin>
			<xmax>1839</xmax>
			<ymax>326</ymax>
		</bndbox>
	</object>
</annotation>
